{"title":"KOBIS ─ 일별 박스오피스","url":"https://www.kobis.or.kr/kobis/mobile/main/findDailyBoxOfficeList.do","favicon":"https://www.kobis.or.kr/kobis/mobile/main/favicon.ico","elements":[{"title":"범죄도시3\n\t\t\t\t\t\t\t\t\n\t\t\t\t\t\t\t\t\t(THE ROUNDUP : NO WAY OUT)","contents":"<div class=\"rank\">\n\t                            <span class=\"num\">1</span>\n\t                            \n\t                            \n\t                            \n\t                            \t\n\t                            \t\n\t                            \t\n\t                            \t\t<span class=\"change\"><em class=\"hidetxt keep\">KEEP</em></span>\n\t                            \t\n\t                            \n\t                        </div>\n\t                        \n\t                        <strong class=\"tit ellip\">범죄도시3\n\t\t\t\t\t\t\t\t<span class=\"en ellip\">\n\t\t\t\t\t\t\t\t\t(THE ROUNDUP : NO WAY OUT)\t                        \t\n\t\t\t\t\t\t\t\t</span>                        \t\n\t                        </strong>\n\t                        <dl class=\"info_sales\">\n\t                            <dt class=\"ico_comm ico_sales\">매출액</dt>\n\t                            <dd>\n\t                                1,391,999,945원\n\t                                <span class=\"cumu\">(누적: 78,458,316,430원)</span>\n\t                            </dd>\n\t                        </dl>\n\t                        <dl class=\"info_audience\">\n\t                            <dt class=\"ico_comm ico_audience\">관객 수</dt>\n\t                            <dd>\n\t                                143,290명\n\t                                <span class=\"cumu\">(누적:7,926,139명)</span>\n\t                            </dd>\n\t                        </dl>","link":"javascript:;","retrieved":1685859146767,"image":"https://www.kobis.or.kr/common/mast/movie/2023/05/thumb_x110/thn_71a80a4008364e119471cb94723af423.jpg"},{"title":"트랜스포머: 비스트의 서막\n\t\t\t\t\t\t\t\t\n\t\t\t\t\t\t\t\t\t(Transformers: Rise of the Beasts )","contents":"<div class=\"rank\">\n\t                            <span class=\"num\">2</span>\n\t                            \n\t                            \n\t                            \n\t                            \t\n\t                            \t\n\t                            \t\n\t                            \t\t<span class=\"change\"><em class=\"hidetxt keep\">KEEP</em></span>\n\t                            \t\n\t                            \n\t                        </div>\n\t                        \n\t                        <strong class=\"tit ellip\">트랜스포머: 비스트의 서막\n\t\t\t\t\t\t\t\t<span class=\"en ellip\">\n\t\t\t\t\t\t\t\t\t(Transformers: Rise of the Beasts )\t                        \t\n\t\t\t\t\t\t\t\t</span>                        \t\n\t                        </strong>\n\t                        <dl class=\"info_sales\">\n\t                            <dt class=\"ico_comm ico_sales\">매출액</dt>\n\t                            <dd>\n\t                                235,554,736원\n\t                                <span class=\"cumu\">(누적: 6,059,602,280원)</span>\n\t                            </dd>\n\t                        </dl>\n\t                        <dl class=\"info_audience\">\n\t                            <dt class=\"ico_comm ico_audience\">관객 수</dt>\n\t                            <dd>\n\t                                24,003명\n\t                                <span class=\"cumu\">(누적:593,484명)</span>\n\t                            </dd>\n\t                        </dl>","link":"javascript:;","retrieved":1685859146767,"image":"https://www.kobis.or.kr/common/mast/movie/2023/05/thumb_x110/thn_5807a350e3944bc7aeb8b7e7b7658cf7.jpg"},{"title":"가디언즈 오브 갤럭시: Volume 3\n\t\t\t\t\t\t\t\t\n\t\t\t\t\t\t\t\t\t(Guardians of the Galaxy Volume 3)","contents":"<div class=\"rank\">\n\t                            <span class=\"num\">3</span>\n\t                            \n\t                            \n\t                            \n\t                            \t\n\t                            \t\n\t                            \t\t<span class=\"change\"><em class=\"ico_comm up\">UP</em>1</span>\n\t                            \t\n\t                            \t\n\t                            \n\t                        </div>\n\t                        \n\t                        <strong class=\"tit ellip\">가디언즈 오브 갤럭시: Volume 3\n\t\t\t\t\t\t\t\t<span class=\"en ellip\">\n\t\t\t\t\t\t\t\t\t(Guardians of the Galaxy Volume 3)\t                        \t\n\t\t\t\t\t\t\t\t</span>                        \t\n\t                        </strong>\n\t                        <dl class=\"info_sales\">\n\t                            <dt class=\"ico_comm ico_sales\">매출액</dt>\n\t                            <dd>\n\t                                61,484,093원\n\t                                <span class=\"cumu\">(누적: 43,865,066,348원)</span>\n\t                            </dd>\n\t                        </dl>\n\t                        <dl class=\"info_audience\">\n\t                            <dt class=\"ico_comm ico_audience\">관객 수</dt>\n\t                            <dd>\n\t                                6,106명\n\t                                <span class=\"cumu\">(누적:4,161,310명)</span>\n\t                            </dd>\n\t                        </dl>","link":"javascript:;","retrieved":1685859146767,"image":"https://www.kobis.or.kr/common/mast/movie/2023/05/thumb_x110/thn_1073d2e8cca44222a3573d0c25b1c581.jpg"},{"title":"분노의 질주: 라이드 오어 다이\n\t\t\t\t\t\t\t\t\n\t\t\t\t\t\t\t\t\t(Fast X)","contents":"<div class=\"rank\">\n\t                            <span class=\"num\">4</span>\n\t                            \n\t                            \n\t                            \n\t                            \t\n\t                            \t\n\t                            \t\t<span class=\"change\"><em class=\"ico_comm up\">UP</em>2</span>\n\t                            \t\n\t                            \t\n\t                            \n\t                        </div>\n\t                        \n\t                        <strong class=\"tit ellip\">분노의 질주: 라이드 오어 다이\n\t\t\t\t\t\t\t\t<span class=\"en ellip\">\n\t\t\t\t\t\t\t\t\t(Fast X)\t                        \t\n\t\t\t\t\t\t\t\t</span>                        \t\n\t                        </strong>\n\t                        <dl class=\"info_sales\">\n\t                            <dt class=\"ico_comm ico_sales\">매출액</dt>\n\t                            <dd>\n\t                                26,217,421원\n\t                                <span class=\"cumu\">(누적: 18,367,800,828원)</span>\n\t                            </dd>\n\t                        </dl>\n\t                        <dl class=\"info_audience\">\n\t                            <dt class=\"ico_comm ico_audience\">관객 수</dt>\n\t                            <dd>\n\t                                2,672명\n\t                                <span class=\"cumu\">(누적:1,762,653명)</span>\n\t                            </dd>\n\t                        </dl>","link":"javascript:;","retrieved":1685859146767,"image":"https://www.kobis.or.kr/common/mast/movie/2023/05/thumb_x110/thn_e37a1df7b75f4962983b511cdfb9507a.jpg"},{"title":"인어공주\n\t\t\t\t\t\t\t\t\n\t\t\t\t\t\t\t\t\t(The Little Mermaid)","contents":"<div class=\"rank\">\n\t                            <span class=\"num\">5</span>\n\t                            \n\t                            \n\t                            \n\t                            \t\n\t                            \t\n\t                            \t\n\t                            \t\t<span class=\"change\"><em class=\"hidetxt keep\">KEEP</em></span>\n\t                            \t\n\t                            \n\t                        </div>\n\t                        \n\t                        <strong class=\"tit ellip\">인어공주\n\t\t\t\t\t\t\t\t<span class=\"en ellip\">\n\t\t\t\t\t\t\t\t\t(The Little Mermaid)\t                        \t\n\t\t\t\t\t\t\t\t</span>                        \t\n\t                        </strong>\n\t                        <dl class=\"info_sales\">\n\t                            <dt class=\"ico_comm ico_sales\">매출액</dt>\n\t                            <dd>\n\t                                17,155,049원\n\t                                <span class=\"cumu\">(누적: 6,520,792,827원)</span>\n\t                            </dd>\n\t                        </dl>\n\t                        <dl class=\"info_audience\">\n\t                            <dt class=\"ico_comm ico_audience\">관객 수</dt>\n\t                            <dd>\n\t                                1,675명\n\t                                <span class=\"cumu\">(누적:633,118명)</span>\n\t                            </dd>\n\t                        </dl>","link":"javascript:;","retrieved":1685859146767,"image":"https://www.kobis.or.kr/common/mast/movie/2023/05/thumb_x110/thn_a94926e45e14463692e6eb4b6600aaaf.jpg"}]}