{"title":"KOBIS ─ 일별 박스오피스 ─ 1위","url":"https://www.kobis.or.kr/kobis/mobile/main/findDailyBoxOfficeList.do","favicon":"https://www.kobis.or.kr/kobis/mobile/main/favicon.ico","elements":[{"title":"관객 수\n\t                            \n\t                                26,131명\n\t                                (누적:4,401,005명)","contents":"스즈메의 문단속\n\t\t\t\t\t\t\t\t<span class=\"en ellip\">\n\t\t\t\t\t\t\t\t\t(Suzume)\t                        \t\n\t\t\t\t\t\t\t\t</span>","link":"javascript:;","retrieved":1674720930140,"image":"https://www.kobis.or.kr/kobis/web/comm/images/noimage110.jpg"}]}