{"title":"KOBIS ─ 주말 박스오피스","url":"https://www.kobis.or.kr/kobis/mobile/main/findWeeklyBoxOfficeList.do?sWeekGb=1","favicon":"https://www.kobis.or.kr/kobis/mobile/main/favicon.ico","elements":[{"title":"베놈 2: 렛 데어 비 카니지\n\t                        \t\n\t\t\t\t\t\t\t\t\t(Venom: Let There Be Carnage)","contents":"<div class=\"rank\">\n\t                            <span class=\"num\">1</span>\n\t                            \n\t                            \n\t                            \n\t                            \t\n\t                            \t\n\t                            \t\n\t                            \t\t<span class=\"change\"><em class=\"hidetxt keep\">KEEP</em></span>\n\t                            \t\n\t                            \n\t                        </div>\n\t                        \n\t                        <strong class=\"tit ellip\">베놈 2: 렛 데어 비 카니지\n\t                        \t<span class=\"en ellip\">\n\t\t\t\t\t\t\t\t\t(Venom: Let There Be Carnage)\t                        \t\n\t\t\t\t\t\t\t\t</span>\n\t                        </strong>\n\t                        <dl class=\"info_sales\">\n\t                            <dt class=\"ico_comm ico_sales\">매출액</dt>\n\t                            <dd>\n\t                                3,468,464,360원\n\t                                <span class=\"cumu\">(누적: 16,481,971,990원)</span>\n\t                            </dd>\n\t                        </dl>\n\t                        <dl class=\"info_audience\">\n\t                            <dt class=\"ico_comm ico_audience\">관객 수</dt>\n\t                            <dd>\n\t                                343,009명\n\t                                <span class=\"cumu\">(누적:1,649,438명)</span>\n\t                            </dd>\n\t                        </dl>","link":"javascript:;","retrieved":1635002428114,"image":"https://www.kobis.or.kr/common/mast/movie/2021/09/thumb_x110/thn_7f0692add69b4b328c23bc88839bb63d.jpg"},{"title":"듄\n\t                        \t\n\t\t\t\t\t\t\t\t\t(DUNE)","contents":"<div class=\"rank\">\n\t                            <span class=\"num\">2</span>\n\t                            \n\t                            \t<span class=\"change\"><em class=\"new\">NEW</em></span>\n\t                            \n\t                            \n\t                            \n\t                        </div>\n\t                        \n\t                        <strong class=\"tit ellip\">듄\n\t                        \t<span class=\"en ellip\">\n\t\t\t\t\t\t\t\t\t(DUNE)\t                        \t\n\t\t\t\t\t\t\t\t</span>\n\t                        </strong>\n\t                        <dl class=\"info_sales\">\n\t                            <dt class=\"ico_comm ico_sales\">매출액</dt>\n\t                            <dd>\n\t                                2,988,622,450원\n\t                                <span class=\"cumu\">(누적: 4,086,635,600원)</span>\n\t                            </dd>\n\t                        </dl>\n\t                        <dl class=\"info_audience\">\n\t                            <dt class=\"ico_comm ico_audience\">관객 수</dt>\n\t                            <dd>\n\t                                275,959명\n\t                                <span class=\"cumu\">(누적:383,173명)</span>\n\t                            </dd>\n\t                        </dl>","link":"javascript:;","retrieved":1635002428114,"image":"https://www.kobis.or.kr/common/mast/movie/2021/09/thumb_x110/thn_4ca094f969b64a4698ecb2ffd72b5fd4.jpg"},{"title":"007 노 타임 투 다이\n\t                        \t\n\t\t\t\t\t\t\t\t\t(007 No Time To Die)","contents":"<div class=\"rank\">\n\t                            <span class=\"num\">3</span>\n\t                            \n\t                            \n\t                            \n\t                            \t\t                            \t\t\n\t                            \t\t<span class=\"change\"><em class=\"ico_comm down\">Down</em>1</span>\t                            \t\t\t                            \t\t\n\t                            \t\n\t                            \t\n\t                            \t\n\t                            \n\t                        </div>\n\t                        \n\t                        <strong class=\"tit ellip\">007 노 타임 투 다이\n\t                        \t<span class=\"en ellip\">\n\t\t\t\t\t\t\t\t\t(007 No Time To Die)\t                        \t\n\t\t\t\t\t\t\t\t</span>\n\t                        </strong>\n\t                        <dl class=\"info_sales\">\n\t                            <dt class=\"ico_comm ico_sales\">매출액</dt>\n\t                            <dd>\n\t                                230,127,360원\n\t                                <span class=\"cumu\">(누적: 11,712,424,390원)</span>\n\t                            </dd>\n\t                        </dl>\n\t                        <dl class=\"info_audience\">\n\t                            <dt class=\"ico_comm ico_audience\">관객 수</dt>\n\t                            <dd>\n\t                                22,821명\n\t                                <span class=\"cumu\">(누적:1,197,221명)</span>\n\t                            </dd>\n\t                        </dl>","link":"javascript:;","retrieved":1635002428114,"image":"https://www.kobis.or.kr/common/mast/movie/2021/09/thumb_x110/thn_95f7b73532b342dcbe4018a869b0bed6.jpg"},{"title":"라스트 듀얼: 최후의 결투\n\t                        \t\n\t\t\t\t\t\t\t\t\t(The Last Duel)","contents":"<div class=\"rank\">\n\t                            <span class=\"num\">4</span>\n\t                            \n\t                            \n\t                            \n\t                            \t\n\t                            \t\n\t                            \t\t<span class=\"change\"><em class=\"ico_comm up\">UP</em>20</span>\n\t                            \t\n\t                            \t\n\t                            \n\t                        </div>\n\t                        \n\t                        <strong class=\"tit ellip\">라스트 듀얼: 최후의 결투\n\t                        \t<span class=\"en ellip\">\n\t\t\t\t\t\t\t\t\t(The Last Duel)\t                        \t\n\t\t\t\t\t\t\t\t</span>\n\t                        </strong>\n\t                        <dl class=\"info_sales\">\n\t                            <dt class=\"ico_comm ico_sales\">매출액</dt>\n\t                            <dd>\n\t                                211,923,610원\n\t                                <span class=\"cumu\">(누적: 323,303,680원)</span>\n\t                            </dd>\n\t                        </dl>\n\t                        <dl class=\"info_audience\">\n\t                            <dt class=\"ico_comm ico_audience\">관객 수</dt>\n\t                            <dd>\n\t                                21,179명\n\t                                <span class=\"cumu\">(누적:33,189명)</span>\n\t                            </dd>\n\t                        </dl>","link":"javascript:;","retrieved":1635002428114,"image":"https://www.kobis.or.kr/common/mast/movie/2021/09/thumb_x110/thn_ad69ab9488f84d1eb373a40a07270aeb.jpg"},{"title":"보이스\n\t                        \t\n\t\t\t\t\t\t\t\t\t(On the Line)","contents":"<div class=\"rank\">\n\t                            <span class=\"num\">5</span>\n\t                            \n\t                            \n\t                            \n\t                            \t\t                            \t\t\n\t                            \t\t<span class=\"change\"><em class=\"ico_comm down\">Down</em>2</span>\t                            \t\t\t                            \t\t\n\t                            \t\n\t                            \t\n\t                            \t\n\t                            \n\t                        </div>\n\t                        \n\t                        <strong class=\"tit ellip\">보이스\n\t                        \t<span class=\"en ellip\">\n\t\t\t\t\t\t\t\t\t(On the Line)\t                        \t\n\t\t\t\t\t\t\t\t</span>\n\t                        </strong>\n\t                        <dl class=\"info_sales\">\n\t                            <dt class=\"ico_comm ico_sales\">매출액</dt>\n\t                            <dd>\n\t                                170,427,390원\n\t                                <span class=\"cumu\">(누적: 13,672,320,140원)</span>\n\t                            </dd>\n\t                        </dl>\n\t                        <dl class=\"info_audience\">\n\t                            <dt class=\"ico_comm ico_audience\">관객 수</dt>\n\t                            <dd>\n\t                                17,572명\n\t                                <span class=\"cumu\">(누적:1,385,837명)</span>\n\t                            </dd>\n\t                        </dl>","link":"javascript:;","retrieved":1635002428114,"image":"https://www.kobis.or.kr/common/mast/movie/2021/08/thumb_x110/thn_698ecc182e614c01887debb0485a12a1.jpg"}]}